{
  "allowedMetrics": [
      {
          "name": "count_crashed_sessions",
          "help": "Count the number of sessions that crashed",
          "type": "counter",
          "labels": [
              {
                  "name": "appName",
                  "allowedValues": [
                      "campus-app"
                  ]
              },
              {
                  "name": "multiplexerUrl",
                  "allowedValues": [
                    "https://multiplexer-prod.datacamp.com",
                    "https://multiplexer-paid.datacamp.com"          
                  ]
              }
          ]
      },
      {
          "name": "time_workspace_to_be_ready",
          "help": "measures the time to get the workspace ready for a user",
          "type": "histogram",
          "labels": [
            {
                "name": "appName",
                "allowedValues": [
                    "campus-app"
                ]
            },
            {
                "name": "multiplexerUrl",
                "allowedValues": [
                  "https://multiplexer-prod.datacamp.com",
                  "https://multiplexer-paid.datacamp.com"          
                ]
            },
            {
                "name": "language",
                "allowedValues": ["r", "revo", "sql", "python", "shell"]
            }
          ],
          "buckets": [
            0.01,
            0.1,
            0.3,
            0.5,
            0.7,
            1,
            1.5,
            2,
            3,
            4,
            5,
            7,
            10,
            15,
            20,
            25,
            30,
            40,
            60
          ]
      },
      {
          "name": "time_to_submit_code",
          "help": "measures the time to submit a code and get the response",
          "type": "histogram",
          "labels": [
            {
                "name": "appName",
                "allowedValues": [
                    "campus-app"
                ]
            },
            {
                "name": "multiplexerUrl",
                "allowedValues": [
                  "https://multiplexer-prod.datacamp.com",
                  "https://multiplexer-paid.datacamp.com"          
                ]
            },
            {
                "name": "language",
                "allowedValues": ["r", "revo", "sql", "python", "shell"]
            }
          ],
          "buckets": [
            0.01,
            0.1,
            0.3,
            0.5,
            0.7,
            1,
            1.5,
            2,
            3,
            4,
            5,
            7,
            10,
            15,
            20,
            25,
            30,
            40,
            60
          ]
      },
      {
          "name": "count_report_sent",
          "help": "Count the number of reports reported",
          "type": "counter",
          "labels": [
            {
                "name": "appName",
                "allowedValues": [
                    "campus-app"
                ]
            }
        ]
      }
  ]
}